screenshotpath/__init__.py
screenshotpath/screenshotpath.py
screenshotpath-0.2.1.dist-info/LICENSE
screenshotpath-0.2.1.dist-info/METADATA
screenshotpath-0.2.1.dist-info/WHEEL
screenshotpath-0.2.1.dist-info/entry_points.txt
screenshotpath-0.2.1.dist-info/top_level.txt
screenshotpath-0.2.1.dist-info/RECORD
