Metadata-Version: 2.1
Name: screenshotpath
Version: 0.2.1
Summary: A package to change macOS screenshot path
Home-page: http://github.com/boiwantlearncode/screenshotpath
Author: Isa Bin Mohamed Yamin
Author-email: boiwantlearncode@gmail.com
License: UNKNOWN
Platform: UNKNOWN
License-File: LICENSE
Requires-Dist: argparse
